aiidalab_widgets_base/__init__.py
aiidalab_widgets_base/bug_report.py
aiidalab_widgets_base/computational_resources.py
aiidalab_widgets_base/databases.py
aiidalab_widgets_base/dicts.py
aiidalab_widgets_base/elns.py
aiidalab_widgets_base/export.py
aiidalab_widgets_base/loaders.py
aiidalab_widgets_base/misc.py
aiidalab_widgets_base/nodes.py
aiidalab_widgets_base/process.py
aiidalab_widgets_base/structures.py
aiidalab_widgets_base/viewers.py
aiidalab_widgets_base/wizard.py
aiidalab_widgets_base/data/__init__.py
aiidalab_widgets_base/static/__init__.py
aiidalab_widgets_base/static/styles/__init__.py
aiidalab_widgets_base/static/styles/global.css
aiidalab_widgets_base/utils/__init__.py
aiidalab_widgets_base/utils/exceptions.py
aiidalab_widgets_base/utils/loaders.py
aiidalab_widgets_base-2.5.0.dist-info/licenses/LICENSE.txt
aiidalab_widgets_base-2.5.0.dist-info/METADATA
aiidalab_widgets_base-2.5.0.dist-info/WHEEL
aiidalab_widgets_base-2.5.0.dist-info/top_level.txt
aiidalab_widgets_base-2.5.0.dist-info/RECORD
