Metadata-Version: 2.4
Name: aiidalab_widgets_base
Version: 2.5.0
Summary: Reusable widgets for AiiDAlab applications.
Home-page: https://github.com/aiidalab/aiidalab-widgets-base
Author: The AiiDAlab team
Author-email: aiidalab@materialscloud.org
License: MIT
Classifier: Development Status :: 5 - Production/Stable
Classifier: Framework :: AiiDA
Classifier: License :: OSI Approved :: MIT License
Classifier: Programming Language :: Python :: 3
Classifier: Programming Language :: Python :: 3 :: Only
Requires-Python: >=3.9
License-File: LICENSE.txt
Requires-Dist: PyCifRW~=4.4
Requires-Dist: aiida-core<3,>=2.2
Requires-Dist: aiidalab>=21.11.2
Requires-Dist: ansi2html~=1.6
Requires-Dist: ase~=3.18
Requires-Dist: bokeh~=2.4
Requires-Dist: humanfriendly~=10.0
Requires-Dist: ipytree~=0.2
Requires-Dist: traitlets~=5.4
Requires-Dist: ipywidgets~=7.7
Requires-Dist: widgetsnbextension<3.6.3
Requires-Dist: pymysql~=0.9
Requires-Dist: nglview>=3.0.8,~=3.0
Requires-Dist: spglib<3,>=1.14
Requires-Dist: vapory~=0.1.2
Requires-Dist: pandas~=2.1
Requires-Dist: ipython<9.0,>=7.33
Provides-Extra: dev
Requires-Dist: bumpver>=2023.1129; extra == "dev"
Requires-Dist: pgtest~=1.3; extra == "dev"
Requires-Dist: pre-commit>=4.0; extra == "dev"
Requires-Dist: pytest~=8.3.0; extra == "dev"
Requires-Dist: pytest-cov~=5.0; extra == "dev"
Requires-Dist: pytest-docker~=3.1.0; extra == "dev"
Requires-Dist: pytest-selenium~=4.1.0; extra == "dev"
Requires-Dist: pytest-timeout~=2.3.0; extra == "dev"
Requires-Dist: selenium~=4.23.0; extra == "dev"
Provides-Extra: optimade
Requires-Dist: ipyoptimade<2,>=1.2.1; extra == "optimade"
Provides-Extra: eln
Requires-Dist: aiidalab-eln>=0.1.2,~=0.1; extra == "eln"
Requires-Dist: requests-cache~=1.0; extra == "eln"
Provides-Extra: smiles
Requires-Dist: rdkit>=2021.09.2; extra == "smiles"
Provides-Extra: docs
Requires-Dist: sphinx~=7.3; extra == "docs"
Requires-Dist: sphinx-design~=0.5; extra == "docs"
Requires-Dist: pydata-sphinx-theme~=0.15; extra == "docs"
Requires-Dist: myst-nb~=1.1; extra == "docs"
Dynamic: license-file
